{
	"format_version": "1.20.40",
	"minecraft:recipe_shaped": {
		"description": {
			"identifier": "hax:lead_cleaver"
		},

    
		"tags": [ "lead_blueprint" ],
		"pattern": [
			" SS",
			"BP ",
			"/  "
		],

		"key": {
			"S": {
				"item": "hax:lead_shortblade"
			},
			"B": {
				"item": "hax:lead_bar"
			},
			"P": {
				"item": "hax:lead_plating"
			},
			"/": {
				"item": "minecraft:stick"
			}
		},


		"unlock": [
			{
				"item": "hax:lead_blueprint"
			}
		],
		"result": { "item": "hax:lead_cleaver" }
	}
}
